click_conf.py
setup.py
click_conf.egg-info/PKG-INFO
click_conf.egg-info/SOURCES.txt
click_conf.egg-info/dependency_links.txt
click_conf.egg-info/requires.txt
click_conf.egg-info/top_level.txt