Metadata-Version: 1.0
Name: click-conf
Version: 0.0.1
Summary: Load default click configurations from file
Home-page: https://github.com/Moshe/click-conf
Author: Moshe Zada
Author-email: UNKNOWN
License: UNKNOWN
Keywords: click,conf,cli,yaml,python,json,config
Platform: UNKNOWN
